pdbapi/__init__.py
pdbapi/data.py
pdbapi/exception.py
pdbapi/file.py
pdbapi/py.typed
pdbapi/typing.py
pdbapi/util.py
pdbapi-0.2.0.dist-info/METADATA
pdbapi-0.2.0.dist-info/WHEEL
pdbapi-0.2.0.dist-info/top_level.txt
pdbapi-0.2.0.dist-info/RECORD
