Metadata-Version: 2.4
Name: PDBAPI
Version: 0.2.0
Summary: Python library for accessing RCSB Protein Data Bank (PDB) data and files
License: MIT
Project-URL: Homepage, https://github.com/scinformatic/pdbapi
Project-URL: Documentation, https://github.com/scinformatic/pdbapi/blob/main/README.md
Project-URL: Repository, https://github.com/scinformatic/pdbapi
Project-URL: Bug Tracker, https://github.com/scinformatic/pdbapi/issues
Keywords: pdb,protein,structure,bioinformatics,rcsb,api
Classifier: Development Status :: 4 - Beta
Classifier: Intended Audience :: Science/Research
Classifier: Intended Audience :: Developers
Classifier: License :: OSI Approved :: MIT License
Classifier: Operating System :: OS Independent
Classifier: Programming Language :: Python :: 3
Classifier: Programming Language :: Python :: 3.10
Classifier: Programming Language :: Python :: 3.11
Classifier: Programming Language :: Python :: 3.12
Classifier: Programming Language :: Python :: 3.13
Classifier: Topic :: Scientific/Engineering :: Bio-Informatics
Classifier: Topic :: Software Development :: Libraries :: Python Modules
Classifier: Typing :: Typed
Requires-Python: >=3.12
Requires-Dist: pylinks<0.2,>=0.1.0
Provides-Extra: dev
Requires-Dist: pytest>=7.0; extra == "dev"
Requires-Dist: pytest-cov>=4.0; extra == "dev"
Requires-Dist: pytest-mock>=3.10; extra == "dev"
Requires-Dist: black>=23.0; extra == "dev"
Requires-Dist: ruff>=0.1.0; extra == "dev"
Requires-Dist: mypy>=1.0; extra == "dev"
